mcts_gen/__init__.py
mcts_gen/fastmcp_server.py
mcts_gen/games/__init__.py
mcts_gen/games/chess_mcts.py
mcts_gen/games/dummy_game.py
mcts_gen/games/ligand_mcts.py
mcts_gen/games/shogi_mcts.py
mcts_gen/models/__init__.py
mcts_gen/models/game_state.py
mcts_gen/services/__init__.py
mcts_gen/services/ai_gp_simulator.py
mcts_gen/services/mcts_engine.py
mcts_gen-0.0.3.dist-info/licenses/LICENSE.txt
mcts_gen-0.0.3.dist-info/METADATA
mcts_gen-0.0.3.dist-info/WHEEL
mcts_gen-0.0.3.dist-info/top_level.txt
mcts_gen-0.0.3.dist-info/RECORD
