Metadata-Version: 2.4
Name: mcts-gen
Version: 0.0.3
Summary: A generic MCTS framework driven by an external AI agent.
Author: Gemini, Perplexity, ChatGPT
Author-email: Akihiro Kuroiwa <akuroiwa@env-reform.com>
License-Expression: GPL-3.0-or-later
Project-URL: Homepage, https://github.com/akuroiwa/mcts-gen
Project-URL: Documentation, https://mcts-gen.readthedocs.io/en/latest/
Project-URL: Repository, https://github.com/akuroiwa/mcts-gen.git
Classifier: Development Status :: 4 - Beta
Classifier: Intended Audience :: Developers
Classifier: Topic :: Software Development :: Libraries :: Python Modules
Classifier: Topic :: Scientific/Engineering :: Artificial Intelligence
Classifier: Programming Language :: Python :: 3.12
Requires-Python: >=3.10
License-File: LICENSE.txt
Requires-Dist: fastmcp
Requires-Dist: mcts
Requires-Dist: mcts-solver
Provides-Extra: dev
Requires-Dist: pytest; extra == "dev"
Requires-Dist: sphinx; extra == "dev"
Requires-Dist: sphinx-intl; extra == "dev"
Requires-Dist: sphinx_rtd_theme; extra == "dev"
Requires-Dist: trio; extra == "dev"
Requires-Dist: trio-typing; extra == "dev"
Requires-Dist: pandas; extra == "dev"
Requires-Dist: mock; extra == "dev"
Provides-Extra: shogi
Requires-Dist: python-shogi; extra == "shogi"
Provides-Extra: chess
Requires-Dist: python-chess; extra == "chess"
Provides-Extra: ligand
Requires-Dist: rdkit; extra == "ligand"
Requires-Dist: pandas; extra == "ligand"
Dynamic: license-file
